qatest/__init__.py
qatest/cli.py
qatest/client.py
qatest/models.py
qatest/uploader.py
qatest/utils.py
qatest/validator.py
qatest-1.0.4.dist-info/licenses/LICENSE
qatest-1.0.4.dist-info/METADATA
qatest-1.0.4.dist-info/WHEEL
qatest-1.0.4.dist-info/entry_points.txt
qatest-1.0.4.dist-info/top_level.txt
qatest-1.0.4.dist-info/RECORD
