Metadata-Version: 2.4
Name: qatest
Version: 1.0.4
Summary: Test case management tool for uploading JSON test cases to QATest
Home-page: https://github.com/yourusername/qatest-cli
Author: QATest Team
Author-email: 
License-Expression: MIT
Project-URL: Homepage, https://github.com/yourusername/qatest-cli
Project-URL: Bug Reports, https://github.com/yourusername/qatest-cli/issues
Project-URL: Source, https://github.com/yourusername/qatest-cli
Keywords: testing,qa,test-cases,test-management,json-upload
Classifier: Development Status :: 3 - Alpha
Classifier: Intended Audience :: Developers
Classifier: Topic :: Software Development :: Testing
Classifier: Programming Language :: Python :: 3
Classifier: Programming Language :: Python :: 3.8
Classifier: Programming Language :: Python :: 3.9
Classifier: Programming Language :: Python :: 3.10
Classifier: Programming Language :: Python :: 3.11
Classifier: Programming Language :: Python :: 3.12
Requires-Python: >=3.8
License-File: LICENSE
Requires-Dist: click>=8.1.0
Requires-Dist: requests>=2.31.0
Requires-Dist: pydantic>=2.0.0
Requires-Dist: python-dotenv>=1.0.0
Requires-Dist: rich>=13.0.0
Requires-Dist: pyyaml>=6.0.0
Dynamic: home-page
Dynamic: license-file
Dynamic: requires-python
